{
  "routes": [
    {
      "method": "GET",
      "path": "/question-a-choix-multiples",
      "handler": "question-a-choix-multiples.find",
      "config": {
        "policies": []
      }
    },
    {
      "method": "GET",
      "path": "/question-a-choix-multiples/count",
      "handler": "question-a-choix-multiples.count",
      "config": {
        "policies": []
      }
    },
    {
      "method": "GET",
      "path": "/question-a-choix-multiples/:id",
      "handler": "question-a-choix-multiples.findOne",
      "config": {
        "policies": []
      }
    },
    {
      "method": "POST",
      "path": "/question-a-choix-multiples",
      "handler": "question-a-choix-multiples.create",
      "config": {
        "policies": []
      }
    },
    {
      "method": "PUT",
      "path": "/question-a-choix-multiples/:id",
      "handler": "question-a-choix-multiples.update",
      "config": {
        "policies": []
      }
    },
    {
      "method": "DELETE",
      "path": "/question-a-choix-multiples/:id",
      "handler": "question-a-choix-multiples.delete",
      "config": {
        "policies": []
      }
    }
  ]
}
